dislog/__init__.py
dislog/handler.py
discord_webhook_logger-1.2.0.dist-info/LICENSE
discord_webhook_logger-1.2.0.dist-info/METADATA
discord_webhook_logger-1.2.0.dist-info/WHEEL
discord_webhook_logger-1.2.0.dist-info/top_level.txt
discord_webhook_logger-1.2.0.dist-info/RECORD
