Metadata-Version: 2.1
Name: discord-webhook-logger
Version: 1.2.0
Summary: Provides an interface for using a discord webhook as a logger.
Home-page: https://github.com/regulad/DiscordWebhookLogger
Author: regulad
Author-email: regulad@outlook.com
License: GPLv3
Download-URL: https://github.com/regulad/DiscordWebhookLogger/archive/refs/heads/master.zip
Keywords: requests
Platform: UNKNOWN
Classifier: Intended Audience :: Developers
Classifier: License :: OSI Approved :: GNU General Public License v3 (GPLv3)
Classifier: Programming Language :: Python :: 3
Classifier: Programming Language :: Python :: 3.6
Classifier: Programming Language :: Python :: 3.7
Classifier: Programming Language :: Python :: 3.8
Classifier: Programming Language :: Python :: 3.9
Classifier: Programming Language :: Python :: 3.10
License-File: LICENSE
Requires-Dist: requests (<3,>=2.27.1)
Requires-Dist: python-version (>="3.6")
